{
    "openapi": "3.0.0",
    "info": {
        "title": "Test Project ciph3r",
        "description": "Documentacion del API",
        "license": {
            "name": "Apache 2.0",
            "url": "https://www.apache.org/licenses/LICENSE-2.0.html"
        },
        "version": "1.0.0"
    },
    "paths": {
        "/api/login": {
            "post": {
                "tags": [
                    "Autenticación"
                ],
                "summary": "Inicio de sesión",
                "operationId": "a3b306d14572d1f4bd6c064b3233e7b8",
                "requestBody": {
                    "required": true,
                    "content": {
                        "application/json": {
                            "schema": {
                                "required": [
                                    "email",
                                    "password"
                                ],
                                "properties": {
                                    "email": {
                                        "type": "string",
                                        "format": "email",
                                        "example": "test@example.com"
                                    },
                                    "password": {
                                        "type": "string",
                                        "format": "password",
                                        "example": "password"
                                    }
                                },
                                "type": "object"
                            }
                        }
                    }
                },
                "responses": {
                    "200": {
                        "description": "Login exitoso",
                        "content": {
                            "application/json": {
                                "schema": {
                                    "properties": {
                                        "access_token": {
                                            "type": "string",
                                            "example": "eyJ0eXAiOiJKV1QiLCJhbGciOiJIUzI1NiJ9..."
                                        },
                                        "token_type": {
                                            "type": "string",
                                            "example": "bearer"
                                        },
                                        "expires_in": {
                                            "type": "integer",
                                            "example": 3600
                                        }
                                    },
                                    "type": "object"
                                }
                            }
                        }
                    },
                    "401": {
                        "description": "Credenciales inválidas",
                        "content": {
                            "application/json": {
                                "schema": {
                                    "properties": {
                                        "error": {
                                            "type": "string",
                                            "example": "Unauthorized"
                                        }
                                    },
                                    "type": "object"
                                }
                            }
                        }
                    }
                }
            }
        },
        "/api/products": {
            "get": {
                "tags": [
                    "Productos"
                ],
                "summary": "Listar todos los productos",
                "operationId": "1bfaa78d1c2c3848ab8165c5dadcad3e",
                "responses": {
                    "200": {
                        "description": "Lista de productos con sus monedas",
                        "content": {
                            "application/json": {
                                "schema": {
                                    "type": "array",
                                    "items": {
                                        "properties": {
                                            "id": {
                                                "type": "integer",
                                                "example": 1
                                            },
                                            "name": {
                                                "type": "string",
                                                "example": "Test Update22"
                                            },
                                            "description": {
                                                "type": "string",
                                                "example": "Description test update."
                                            },
                                            "price": {
                                                "type": "number",
                                                "format": "float",
                                                "example": 1000.1
                                            },
                                            "currency_id": {
                                                "type": "integer",
                                                "example": 1
                                            },
                                            "tax_cost": {
                                                "type": "number",
                                                "format": "float",
                                                "example": 15.01
                                            },
                                            "manufacturing_cost": {
                                                "type": "number",
                                                "format": "float",
                                                "example": 357.66
                                            },
                                            "created_at": {
                                                "type": "string",
                                                "format": "date-time",
                                                "example": "2025-03-12T18:21:39.000000Z"
                                            },
                                            "updated_at": {
                                                "type": "string",
                                                "format": "date-time",
                                                "example": "2025-03-12T20:06:33.000000Z"
                                            },
                                            "currency": {
                                                "properties": {
                                                    "id": {
                                                        "type": "integer",
                                                        "example": 1
                                                    },
                                                    "name": {
                                                        "type": "string",
                                                        "example": "US Dollar"
                                                    },
                                                    "symbol": {
                                                        "type": "string",
                                                        "example": "USD"
                                                    },
                                                    "exchange_rate": {
                                                        "type": "number",
                                                        "format": "float",
                                                        "example": 1
                                                    },
                                                    "created_at": {
                                                        "type": "string",
                                                        "format": "date-time",
                                                        "example": "2025-03-12T18:21:39.000000Z"
                                                    },
                                                    "updated_at": {
                                                        "type": "string",
                                                        "format": "date-time",
                                                        "example": "2025-03-12T18:21:39.000000Z"
                                                    }
                                                },
                                                "type": "object"
                                            }
                                        },
                                        "type": "object"
                                    }
                                }
                            }
                        }
                    }
                }
            },
            "post": {
                "tags": [
                    "Productos"
                ],
                "summary": "Crear un nuevo producto",
                "operationId": "e8185e307706e2cd84bbcf5171e2f09d",
                "requestBody": {
                    "required": true,
                    "content": {
                        "application/json": {
                            "schema": {
                                "required": [
                                    "name",
                                    "price",
                                    "currency_id",
                                    "tax_cost",
                                    "manufacturing_cost"
                                ],
                                "properties": {
                                    "name": {
                                        "type": "string",
                                        "example": "Test Create"
                                    },
                                    "description": {
                                        "type": "string",
                                        "example": "Description test create."
                                    },
                                    "price": {
                                        "type": "number",
                                        "format": "float",
                                        "example": 1455.1
                                    },
                                    "currency_id": {
                                        "type": "integer",
                                        "example": 2
                                    },
                                    "tax_cost": {
                                        "type": "number",
                                        "format": "float",
                                        "example": 15.01
                                    },
                                    "manufacturing_cost": {
                                        "type": "number",
                                        "format": "float",
                                        "example": 357.66
                                    }
                                },
                                "type": "object"
                            }
                        }
                    }
                },
                "responses": {
                    "201": {
                        "description": "Producto creado exitosamente",
                        "content": {
                            "application/json": {
                                "schema": {
                                    "properties": {
                                        "id": {
                                            "type": "integer",
                                            "example": 13
                                        },
                                        "name": {
                                            "type": "string",
                                            "example": "Test Create"
                                        },
                                        "description": {
                                            "type": "string",
                                            "example": "Description test create."
                                        },
                                        "price": {
                                            "type": "number",
                                            "format": "float",
                                            "example": 1455.1
                                        },
                                        "currency_id": {
                                            "type": "integer",
                                            "example": 2
                                        },
                                        "tax_cost": {
                                            "type": "number",
                                            "format": "float",
                                            "example": 15.01
                                        },
                                        "manufacturing_cost": {
                                            "type": "number",
                                            "format": "float",
                                            "example": 357.66
                                        },
                                        "created_at": {
                                            "type": "string",
                                            "format": "date-time",
                                            "example": "2025-03-12T20:46:05.000000Z"
                                        },
                                        "updated_at": {
                                            "type": "string",
                                            "format": "date-time",
                                            "example": "2025-03-12T20:46:05.000000Z"
                                        }
                                    },
                                    "type": "object"
                                }
                            }
                        }
                    },
                    "422": {
                        "description": "Error de validación",
                        "content": {
                            "application/json": {
                                "schema": {
                                    "properties": {
                                        "message": {
                                            "type": "string",
                                            "example": "El campo name es obligatorio."
                                        },
                                        "errors": {
                                            "properties": {
                                                "name": {
                                                    "type": "array",
                                                    "items": {
                                                        "type": "string",
                                                        "example": "El campo name es obligatorio."
                                                    }
                                                }
                                            },
                                            "type": "object"
                                        }
                                    },
                                    "type": "object"
                                }
                            }
                        }
                    }
                }
            }
        },
        "/api/products/{id}": {
            "get": {
                "tags": [
                    "Productos"
                ],
                "summary": "Obtener detalles de un producto",
                "operationId": "7ab21ddb713501f3d4c2914892c02a21",
                "parameters": [
                    {
                        "name": "id",
                        "in": "path",
                        "description": "ID del producto",
                        "required": true,
                        "schema": {
                            "type": "integer",
                            "example": 1
                        }
                    }
                ],
                "responses": {
                    "200": {
                        "description": "Detalles del producto",
                        "content": {
                            "application/json": {
                                "schema": {
                                    "properties": {
                                        "status": {
                                            "type": "string",
                                            "example": "success"
                                        },
                                        "data": {
                                            "properties": {
                                                "id": {
                                                    "type": "integer",
                                                    "example": 1
                                                },
                                                "name": {
                                                    "type": "string",
                                                    "example": "Test Product"
                                                },
                                                "description": {
                                                    "type": "string",
                                                    "example": "Description test"
                                                },
                                                "price": {
                                                    "type": "number",
                                                    "format": "float",
                                                    "example": 1000.1
                                                },
                                                "currency_id": {
                                                    "type": "integer",
                                                    "example": 1
                                                },
                                                "currency": {
                                                    "properties": {
                                                        "id": {
                                                            "type": "integer",
                                                            "example": 1
                                                        },
                                                        "name": {
                                                            "type": "string",
                                                            "example": "US Dollar"
                                                        },
                                                        "symbol": {
                                                            "type": "string",
                                                            "example": "USD"
                                                        },
                                                        "exchange_rate": {
                                                            "type": "string",
                                                            "example": "1.0000"
                                                        }
                                                    },
                                                    "type": "object"
                                                }
                                            },
                                            "type": "object"
                                        }
                                    },
                                    "type": "object"
                                }
                            }
                        }
                    },
                    "404": {
                        "description": "Producto no encontrado",
                        "content": {
                            "application/json": {
                                "schema": {
                                    "properties": {
                                        "message": {
                                            "type": "string",
                                            "example": "Producto no encontrado"
                                        }
                                    },
                                    "type": "object"
                                }
                            }
                        }
                    }
                }
            },
            "put": {
                "tags": [
                    "Productos"
                ],
                "summary": "Actualizar un producto",
                "operationId": "6a7e11900844cd85cff66e662b82bd4c",
                "parameters": [
                    {
                        "name": "id",
                        "in": "path",
                        "description": "ID del producto",
                        "required": true,
                        "schema": {
                            "type": "integer",
                            "example": 1
                        }
                    }
                ],
                "requestBody": {
                    "required": true,
                    "content": {
                        "application/json": {
                            "schema": {
                                "properties": {
                                    "name": {
                                        "type": "string",
                                        "example": "Updated Product"
                                    },
                                    "description": {
                                        "type": "string",
                                        "example": "Updated description"
                                    },
                                    "price": {
                                        "type": "number",
                                        "format": "float",
                                        "example": 1200.5
                                    },
                                    "currency_id": {
                                        "type": "integer",
                                        "example": 1
                                    },
                                    "tax_cost": {
                                        "type": "number",
                                        "format": "float",
                                        "example": 20
                                    },
                                    "manufacturing_cost": {
                                        "type": "number",
                                        "format": "float",
                                        "example": 400.75
                                    }
                                },
                                "type": "object"
                            }
                        }
                    }
                },
                "responses": {
                    "200": {
                        "description": "Producto actualizado exitosamente",
                        "content": {
                            "application/json": {
                                "schema": {
                                    "properties": {
                                        "id": {
                                            "type": "integer",
                                            "example": 1
                                        },
                                        "name": {
                                            "type": "string",
                                            "example": "Updated Product"
                                        },
                                        "description": {
                                            "type": "string",
                                            "example": "Updated description"
                                        },
                                        "price": {
                                            "type": "number",
                                            "format": "float",
                                            "example": 1200.5
                                        },
                                        "currency_id": {
                                            "type": "integer",
                                            "example": 1
                                        },
                                        "tax_cost": {
                                            "type": "number",
                                            "format": "float",
                                            "example": 20
                                        },
                                        "manufacturing_cost": {
                                            "type": "number",
                                            "format": "float",
                                            "example": 400.75
                                        },
                                        "updated_at": {
                                            "type": "string",
                                            "format": "date-time",
                                            "example": "2025-03-12T21:00:00.000000Z"
                                        }
                                    },
                                    "type": "object"
                                }
                            }
                        }
                    },
                    "404": {
                        "description": "Producto no encontrado",
                        "content": {
                            "application/json": {
                                "schema": {
                                    "properties": {
                                        "message": {
                                            "type": "string",
                                            "example": "Producto no encontrado"
                                        }
                                    },
                                    "type": "object"
                                }
                            }
                        }
                    },
                    "422": {
                        "description": "Error de validación",
                        "content": {
                            "application/json": {
                                "schema": {
                                    "properties": {
                                        "message": {
                                            "type": "string",
                                            "example": "El campo name es obligatorio."
                                        },
                                        "errors": {
                                            "properties": {
                                                "name": {
                                                    "type": "array",
                                                    "items": {
                                                        "type": "string",
                                                        "example": "El campo name es obligatorio."
                                                    }
                                                }
                                            },
                                            "type": "object"
                                        }
                                    },
                                    "type": "object"
                                }
                            }
                        }
                    }
                }
            },
            "delete": {
                "tags": [
                    "Productos"
                ],
                "summary": "Eliminar un producto",
                "operationId": "e80a6ca46716acee6b47ea1ac91663c0",
                "parameters": [
                    {
                        "name": "id",
                        "in": "path",
                        "description": "ID del producto",
                        "required": true,
                        "schema": {
                            "type": "integer",
                            "example": 1
                        }
                    }
                ],
                "responses": {
                    "204": {
                        "description": "Producto eliminado exitosamente"
                    },
                    "404": {
                        "description": "Producto no encontrado",
                        "content": {
                            "application/json": {
                                "schema": {
                                    "properties": {
                                        "message": {
                                            "type": "string",
                                            "example": "Producto no encontrado"
                                        }
                                    },
                                    "type": "object"
                                }
                            }
                        }
                    }
                }
            }
        },
        "/api/products/{id}/prices": {
            "get": {
                "tags": [
                    "Productos"
                ],
                "summary": "Obtener los precios de un producto en diferentes monedas",
                "operationId": "c344001ef9e38ce3a9a475ff2f6de5a7",
                "parameters": [
                    {
                        "name": "id",
                        "in": "path",
                        "description": "ID del producto",
                        "required": true,
                        "schema": {
                            "type": "integer",
                            "example": 10
                        }
                    }
                ],
                "responses": {
                    "200": {
                        "description": "Lista de precios del producto en distintas monedas",
                        "content": {
                            "application/json": {
                                "schema": {
                                    "type": "array",
                                    "items": {
                                        "properties": {
                                            "id": {
                                                "type": "integer",
                                                "example": 19
                                            },
                                            "product_id": {
                                                "type": "integer",
                                                "example": 10
                                            },
                                            "currency_id": {
                                                "type": "integer",
                                                "example": 1
                                            },
                                            "price": {
                                                "type": "string",
                                                "example": "0.15"
                                            },
                                            "created_at": {
                                                "type": "string",
                                                "format": "date-time",
                                                "example": "2025-03-12T18:21:39.000000Z"
                                            },
                                            "updated_at": {
                                                "type": "string",
                                                "format": "date-time",
                                                "example": "2025-03-12T18:21:39.000000Z"
                                            },
                                            "currency": {
                                                "properties": {
                                                    "id": {
                                                        "type": "integer",
                                                        "example": 1
                                                    },
                                                    "name": {
                                                        "type": "string",
                                                        "example": "US Dollar"
                                                    },
                                                    "symbol": {
                                                        "type": "string",
                                                        "example": "USD"
                                                    },
                                                    "exchange_rate": {
                                                        "type": "string",
                                                        "example": "1.0000"
                                                    },
                                                    "created_at": {
                                                        "type": "string",
                                                        "format": "date-time",
                                                        "example": "2025-03-12T18:21:39.000000Z"
                                                    },
                                                    "updated_at": {
                                                        "type": "string",
                                                        "format": "date-time",
                                                        "example": "2025-03-12T18:21:39.000000Z"
                                                    }
                                                },
                                                "type": "object"
                                            }
                                        },
                                        "type": "object"
                                    }
                                }
                            }
                        }
                    },
                    "404": {
                        "description": "Producto no encontrado",
                        "content": {
                            "application/json": {
                                "schema": {
                                    "properties": {
                                        "message": {
                                            "type": "string",
                                            "example": "Producto no encontrado"
                                        }
                                    },
                                    "type": "object"
                                }
                            }
                        }
                    }
                }
            },
            "post": {
                "tags": [
                    "Productos"
                ],
                "summary": "Agregar un precio a un producto",
                "operationId": "0a267ed14eb16d878bbec2d44c48cc7b",
                "parameters": [
                    {
                        "name": "id",
                        "in": "path",
                        "description": "ID del producto",
                        "required": true,
                        "schema": {
                            "type": "integer",
                            "example": 6
                        }
                    }
                ],
                "requestBody": {
                    "required": true,
                    "content": {
                        "application/json": {
                            "schema": {
                                "required": [
                                    "currency_id",
                                    "price"
                                ],
                                "properties": {
                                    "currency_id": {
                                        "type": "integer",
                                        "example": 1
                                    },
                                    "price": {
                                        "type": "string",
                                        "example": "2000"
                                    }
                                },
                                "type": "object"
                            }
                        }
                    }
                },
                "responses": {
                    "201": {
                        "description": "Precio agregado exitosamente",
                        "content": {
                            "application/json": {
                                "schema": {
                                    "properties": {
                                        "id": {
                                            "type": "integer",
                                            "example": 31
                                        },
                                        "product_id": {
                                            "type": "integer",
                                            "example": 6
                                        },
                                        "currency_id": {
                                            "type": "integer",
                                            "example": 2
                                        },
                                        "price": {
                                            "type": "string",
                                            "example": "2000"
                                        },
                                        "created_at": {
                                            "type": "string",
                                            "format": "date-time",
                                            "example": "2025-03-12T20:52:36.000000Z"
                                        },
                                        "updated_at": {
                                            "type": "string",
                                            "format": "date-time",
                                            "example": "2025-03-12T20:52:36.000000Z"
                                        }
                                    },
                                    "type": "object"
                                }
                            }
                        }
                    },
                    "422": {
                        "description": "Error de validación",
                        "content": {
                            "application/json": {
                                "schema": {
                                    "properties": {
                                        "message": {
                                            "type": "string",
                                            "example": "El precio es obligatorio"
                                        },
                                        "errors": {
                                            "properties": {
                                                "price": {
                                                    "type": "array",
                                                    "items": {
                                                        "type": "string",
                                                        "example": "El precio debe ser un número"
                                                    }
                                                }
                                            },
                                            "type": "object"
                                        }
                                    },
                                    "type": "object"
                                }
                            }
                        }
                    },
                    "404": {
                        "description": "Producto no encontrado",
                        "content": {
                            "application/json": {
                                "schema": {
                                    "properties": {
                                        "message": {
                                            "type": "string",
                                            "example": "Producto no encontrado"
                                        }
                                    },
                                    "type": "object"
                                }
                            }
                        }
                    }
                }
            }
        }
    },
    "tags": [
        {
            "name": "Autenticación",
            "description": "Autenticación"
        },
        {
            "name": "Productos",
            "description": "Productos"
        }
    ]
}